CHANGELOG.md
LICENSE.BSD3
LICENSE.MIT
LICENSE.md
MANIFEST.in
README.md
setup.py
bCNC/CNC.py
bCNC/CNCCanvas.py
bCNC/CNCList.py
bCNC/CNCRibbon.py
bCNC/Camera.py
bCNC/ControlPage.py
bCNC/EditorPage.py
bCNC/FilePage.py
bCNC/Helpers.py
bCNC/Pendant.py
bCNC/ProbePage.py
bCNC/Ribbon.py
bCNC/Sender.py
bCNC/TerminalPage.py
bCNC/ToolsPage.py
bCNC/Updates.py
bCNC/Utils.py
bCNC/__init__.py
bCNC/__main__.py
bCNC/bCNC
bCNC/bCNC.bat
bCNC/bCNC.desktop
bCNC/bCNC.ico
bCNC/bCNC.ini
bCNC/bCNC.png
bCNC/bCNC.xbm
bCNC/bmain.py
bCNC/make-exe.bat
bCNC/requirements.txt
bCNC.egg-info/PKG-INFO
bCNC.egg-info/SOURCES.txt
bCNC.egg-info/dependency_links.txt
bCNC.egg-info/entry_points.txt
bCNC.egg-info/requires.txt
bCNC.egg-info/top_level.txt
bCNC/controllers/G2Core.py
bCNC/controllers/GRBL0.py
bCNC/controllers/GRBL1.py
bCNC/controllers/SMOOTHIE.py
bCNC/controllers/_GenericController.py
bCNC/controllers/_GenericGRBL.py
bCNC/icons/SimpleArc.gif
bCNC/icons/SimpleDrill.gif
bCNC/icons/SimpleLine.gif
bCNC/icons/SimpleRectangle.gif
bCNC/icons/SimpleRotate.gif
bCNC/icons/SimpleTranslate.gif
bCNC/icons/about.gif
bCNC/icons/add.gif
bCNC/icons/all.gif
bCNC/icons/arcfit.gif
bCNC/icons/arduino.gif
bCNC/icons/axes.gif
bCNC/icons/bCNC.gif
bCNC/icons/bc.gif
bCNC/icons/bl.gif
bCNC/icons/boolean.gif
bCNC/icons/bowl.gif
bCNC/icons/box.gif
bCNC/icons/br.gif
bCNC/icons/calibrate32.gif
bCNC/icons/camera.gif
bCNC/icons/camera32.gif
bCNC/icons/center.gif
bCNC/icons/centerpoint.gif
bCNC/icons/clean32.gif
bCNC/icons/clear.gif
bCNC/icons/climb.gif
bCNC/icons/clone.gif
bCNC/icons/closepath.gif
bCNC/icons/color.gif
bCNC/icons/comment.gif
bCNC/icons/config.gif
bCNC/icons/config32.gif
bCNC/icons/control.gif
bCNC/icons/conventional.gif
bCNC/icons/copy.gif
bCNC/icons/crosshair.gif
bCNC/icons/crosshair32.gif
bCNC/icons/cut.gif
bCNC/icons/cut32.gif
bCNC/icons/debug.gif
bCNC/icons/diff.gif
bCNC/icons/digits.gif
bCNC/icons/disable.gif
bCNC/icons/divide.gif
bCNC/icons/down.gif
bCNC/icons/dragknife.gif
bCNC/icons/drill.gif
bCNC/icons/driller.gif
bCNC/icons/edge.gif
bCNC/icons/edit.gif
bCNC/icons/empty.gif
bCNC/icons/enable.gif
bCNC/icons/endmill.gif
bCNC/icons/endmill32.gif
bCNC/icons/event.gif
