Metadata-Version: 2.2
Name: bCNC
Version: 0.9.16
Summary: Swiss army knife for all your CNC/g-code needs
Home-page: https://github.com/vlachoudis/bCNC
Author: Vasilis Vlachoudis
Author-email: vvlachoudis@gmail.com
License: GPLv2
Classifier: Development Status :: 4 - Beta
Classifier: License :: OSI Approved :: GNU General Public License v2 (GPLv2)
Classifier: Operating System :: OS Independent
Classifier: Topic :: Multimedia :: Graphics :: 3D Modeling
Classifier: Topic :: Multimedia :: Graphics :: Capture
Classifier: Topic :: Multimedia :: Graphics :: Editors :: Vector-Based
Classifier: Topic :: Multimedia :: Graphics :: Graphics Conversion
Classifier: Topic :: Multimedia :: Graphics :: Viewers
Classifier: Topic :: Scientific/Engineering
Classifier: Topic :: Scientific/Engineering :: Electronic Design Automation (EDA)
Classifier: Topic :: Terminals :: Serial
Classifier: Natural Language :: Dutch
Classifier: Natural Language :: English
Classifier: Natural Language :: German
Classifier: Natural Language :: Spanish
Classifier: Natural Language :: Portuguese
Classifier: Natural Language :: Portuguese (Brazilian)
Classifier: Natural Language :: French
Classifier: Natural Language :: Italian
Classifier: Natural Language :: Japanese
Classifier: Natural Language :: Korean
Classifier: Natural Language :: Russian
Classifier: Natural Language :: Chinese (Simplified)
Classifier: Natural Language :: Chinese (Traditional)
License-File: LICENSE.BSD3
License-File: LICENSE.MIT
License-File: LICENSE.md
Requires-Dist: pyobjc; sys_platform == "darwin"
Requires-Dist: pyobjc-core; sys_platform == "darwin"
Requires-Dist: pyobjc-framework-Quartz; sys_platform == "darwin"
Requires-Dist: pyserial; sys_platform != "win32"
Requires-Dist: pyserial<=3.0.1; sys_platform == "win32"
Requires-Dist: numpy>=1.12
Requires-Dist: svgelements<2,>=1
Requires-Dist: shxparser>=0.0.2
Requires-Dist: Pillow>=4.0
Requires-Dist: opencv-python==4.5.5.64; "arm" not in platform_machine and "aarch64" not in platform_machine
Requires-Dist: tkinter-gl>=1.0
Dynamic: author
Dynamic: author-email
Dynamic: classifier
Dynamic: description
Dynamic: description-content-type
Dynamic: home-page
Dynamic: license
Dynamic: requires-dist
Dynamic: summary
